{
  "ext.displayName": "Skill Switch",
  "ext.description": "Manage and switch between AI Skill configurations for CodeBuddy and other AI tools",
  "ext.viewContainerTitle": "Skill Switch",
  "ext.viewName": "Skill Switch",
  "cmd.createProfile": "New Profile",
  "cmd.delete": "Delete",
  "cmd.edit": "Edit Name/Description",
  "cmd.switch": "Activate",
  "cmd.addSkill": "Add Skill",
  "cmd.remove": "Remove",
  "cmd.editFile": "Edit File",
  "cmd.addPermanent": "Add Permanent Skill",
  "cmd.moveToPermanent": "Move to Permanent",
  "cmd.moveToProfile": "Move to Profile...",
  "cmd.copyToProfile": "Copy to Profile...",
  "cmd.addDesignDoc": "Add Design Doc",
  "cmd.openDesignDoc": "Open",
  "cmd.editNameDesc": "Edit Name/Description",
  "cmd.openInExplorer": "Reveal in File Explorer",
  "cmd.newFile": "New File",
  "cmd.newFolder": "New Folder",
  "cmd.refresh": "Refresh",
  "cmd.settings": "Settings",
  "cmd.importSkills": "Import Skills",
  "cmd.backup": "Backup",
  "cmd.restore": "Restore"
}
